psycho/__init__.py
psycho/building.py
psycho/click_types.py
psycho/commands.py
psycho/dependencies.py
psycho/environment.py
psycho/initializing.py
psycho/paths.py
psycho/projects.py
psycho/publishing.py
psycho/uploading.py
psycho/data/README.md
psycho/data/__init__.py
psycho/data/gitignore.txt
psycho-2.1.5.dist-info/METADATA
psycho-2.1.5.dist-info/WHEEL
psycho-2.1.5.dist-info/entry_points.txt
psycho-2.1.5.dist-info/top_level.txt
psycho-2.1.5.dist-info/RECORD
