Metadata-Version: 2.1
Name: psycho
Version: 2.1.5
Summary: A tool to manage python projects and their dependencies.
Author-email: Rob Blackbourn <rob.blackbourn@gmail.com>
License: Apache-2.0
Project-URL: Repository, https://github.com/rob-blackbourn/psycho
Project-URL: Issues, https://github.com/rob-blackbourn/psycho/issues
Keywords: pyproject.toml,pip
Classifier: Development Status :: 2 - Pre-Alpha
Classifier: Environment :: Console
Classifier: Intended Audience :: Developers
Classifier: Operating System :: OS Independent
Classifier: Programming Language :: Python :: 3
Classifier: Programming Language :: Python :: 3.12
Classifier: Programming Language :: Python :: 3.13
Classifier: Topic :: Software Development
Requires-Python: >=3.8
Requires-Dist: click ==8.1.8
Requires-Dist: tomlkit ==0.13.2
Requires-Dist: setuptools ==61.0.0
Requires-Dist: packaging ==24.2
Requires-Dist: build ==1.2.2.post1
Requires-Dist: twine ==6.1.0
Requires-Dist: click-aliases ==1.0.5
